powerset_generator/__about__.py
powerset_generator/__init__.py
powerset_generator/py.typed
powerset_generator-0.1.3.dist-info/METADATA
powerset_generator-0.1.3.dist-info/WHEEL
powerset_generator-0.1.3.dist-info/licenses/LICENSE
powerset_generator-0.1.3.dist-info/RECORD
