Metadata-Version: 2.1
Name: powerset-generator
Version: 0.1.3
Summary: Generate the power set of a collection
Project-URL: Documentation, https://jpgoldberg.github.io/powerset-generator/
Project-URL: Issues, https://github.com/jpgoldberg/powerset-generator/issues
Project-URL: Source, https://github.com/jpgoldberg/powerset-generator
Project-URL: Changelog, https://github.com/jpgoldberg/powerset-generator/blob/main/CHANGELOG.md
Author-email: Jeffrey Goldberg <jeffrey@goldmark.org>
License: MIT Licesne
License-File: LICENSE
Classifier: Development Status :: 4 - Beta
Classifier: Programming Language :: Python
Classifier: Programming Language :: Python :: 3.8
Classifier: Programming Language :: Python :: 3.9
Classifier: Programming Language :: Python :: 3.10
Classifier: Programming Language :: Python :: 3.11
Classifier: Programming Language :: Python :: 3.12
Classifier: Programming Language :: Python :: Implementation :: CPython
Classifier: Programming Language :: Python :: Implementation :: PyPy
Requires-Python: >=3.8
